telegrinder/__init__.py
telegrinder/__meta__.py
telegrinder/model.py
telegrinder/modules.py
telegrinder/py.typed
telegrinder/rules.py
telegrinder/verification_utils.py
telegrinder/api/__init__.py
telegrinder/api/api.py
telegrinder/api/error.py
telegrinder/api/response.py
telegrinder/api/token.py
telegrinder/bot/__init__.py
telegrinder/bot/bot.py
telegrinder/bot/cute_types/__init__.py
telegrinder/bot/cute_types/base.py
telegrinder/bot/cute_types/callback_query.py
telegrinder/bot/cute_types/chat_join_request.py
telegrinder/bot/cute_types/chat_member_updated.py
telegrinder/bot/cute_types/inline_query.py
telegrinder/bot/cute_types/message.py
telegrinder/bot/cute_types/pre_checkout_query.py
telegrinder/bot/cute_types/update.py
telegrinder/bot/cute_types/utils.py
telegrinder/bot/dispatch/__init__.py
telegrinder/bot/dispatch/abc.py
telegrinder/bot/dispatch/action.py
telegrinder/bot/dispatch/context.py
telegrinder/bot/dispatch/dispatch.py
telegrinder/bot/dispatch/process.py
telegrinder/bot/dispatch/handler/__init__.py
telegrinder/bot/dispatch/handler/abc.py
telegrinder/bot/dispatch/handler/audio_reply.py
telegrinder/bot/dispatch/handler/base.py
telegrinder/bot/dispatch/handler/document_reply.py
telegrinder/bot/dispatch/handler/func.py
telegrinder/bot/dispatch/handler/media_group_reply.py
telegrinder/bot/dispatch/handler/message_reply.py
telegrinder/bot/dispatch/handler/photo_reply.py
telegrinder/bot/dispatch/handler/sticker_reply.py
telegrinder/bot/dispatch/handler/video_reply.py
telegrinder/bot/dispatch/middleware/__init__.py
telegrinder/bot/dispatch/middleware/abc.py
telegrinder/bot/dispatch/middleware/global_middleware.py
telegrinder/bot/dispatch/return_manager/__init__.py
telegrinder/bot/dispatch/return_manager/abc.py
telegrinder/bot/dispatch/return_manager/callback_query.py
telegrinder/bot/dispatch/return_manager/inline_query.py
telegrinder/bot/dispatch/return_manager/message.py
telegrinder/bot/dispatch/return_manager/pre_checkout_query.py
telegrinder-0.5.1.dist-info/METADATA
telegrinder-0.5.1.dist-info/WHEEL
telegrinder-0.5.1.dist-info/licenses/LICENSE
telegrinder-0.5.1.dist-info/RECORD
