Metadata-Version: 2.4
Name: telegrinder
Version: 0.5.1
Summary: Modern visionary telegram bot framework.
Project-URL: Source, https://github.com/timoniq/telegrinder
Project-URL: Bug Tracker, https://github.com/timoniq/telegrinder/issues
Project-URL: Documentation, https://github.com/timoniq/telegrinder/blob/dev/docs/index.md
Author-email: timoniq <tesseradecades@mail.ru>
Maintainer-email: luwqz1 <howluwqz1@gmail.com>
License: MIT License
License-File: LICENSE
Keywords: api schema,async,asyncio,bot api,bot building,custom rules,framework,middleware,nodes,telegram,telegram bot api framework,telegrinder,telegrinder framework,waiter machine
Classifier: Environment :: Console
Classifier: Intended Audience :: Developers
Classifier: License :: OSI Approved :: MIT License
Classifier: Programming Language :: Python :: 3.12
Classifier: Programming Language :: Python :: 3.13
Classifier: Topic :: Software Development :: Libraries :: Python Modules
Classifier: Topic :: Software Development :: Quality Assurance
Classifier: Typing :: Typed
Requires-Python: <4.0,>=3.12
Requires-Dist: aiodns<4.0.0,>=3.5.0; sys_platform != 'darwin'
Requires-Dist: aiohttp<4.0.0,>=3.12.13
Requires-Dist: certifi<2026.0.0,>=2025.7.9
Requires-Dist: choicelib<0.2.0,>=0.1.5
Requires-Dist: colorama<0.5.0,>=0.4.6
Requires-Dist: envparse<0.3.0,>=0.2.0
Requires-Dist: funtypes==0.2.1
Requires-Dist: msgspec<0.20.0,>=0.19.0
Requires-Dist: typing-extensions<5.0.0,>=4.14.1
Requires-Dist: vbml<2.0,>=1.1.post1
Provides-Extra: brotli
Requires-Dist: brotli; extra == 'brotli'
Provides-Extra: loguru
Requires-Dist: loguru; extra == 'loguru'
Provides-Extra: socks
Requires-Dist: aiohttp-socks; extra == 'socks'
Provides-Extra: structlog
Requires-Dist: structlog; extra == 'structlog'
Provides-Extra: uvloop
Requires-Dist: uvloop; (sys_platform == 'darwin' or sys_platform == 'linux') and extra == 'uvloop'
Requires-Dist: winloop; (sys_platform == 'cli' or sys_platform == 'cygwin' or sys_platform == 'win32') and extra == 'uvloop'
